fortigatessh/__init__.py
fortigatessh/command_executor.py
fortigatessh/constants.py
fortigatessh/exceptions.py
fortigatessh/fortigate_device.py
fortigatessh/ssh_connection.py
fortigatessh-0.2.1.dist-info/LICENSE
fortigatessh-0.2.1.dist-info/METADATA
fortigatessh-0.2.1.dist-info/WHEEL
fortigatessh-0.2.1.dist-info/top_level.txt
fortigatessh-0.2.1.dist-info/RECORD
