Metadata-Version: 2.1
Name: fortigatessh
Version: 0.2.1
Summary: A Python library for managing FortiGate devices via SSH
Author: Nathan Liang
License: Apache License 2.0
Classifier: Programming Language :: Python :: 3
Classifier: License :: OSI Approved :: Apache Software License
Classifier: Operating System :: OS Independent
Requires-Python: >=3.6
License-File: LICENSE
Requires-Dist: paramiko>=2.7.0
Requires-Dist: paramiko-expect>=0.2.0
